{"id":"4nZxUaZMBAvz7oWuXizXl","title":"PROG","desc":"","updated":1641048648905,"created":1640615341424,"stub":false,"custom":{"stub":true},"fname":"tags.PROG","type":"note","vault":{"fsPath":"vault"},"contentHash":"8849edd60fa4b37edbb7fac19f4ac66a","links":[],"anchors":{},"children":["gj0sitvrk6ynbtxpixc4ih4","zavPiB0ApTq1sGZOGq9xJ","8butragqifg44gfphdug6ys","uFYxvNnYUjt8oxQcHtfSp","3cKSNGeq54iDx1eRKcNB0","ufrvrxg5egfy06vzaaitl1h","1z3qa2rt5zymm05yroq0d7c","Po0jmNACWQVrxnoTRT6kr","hikt5akgz6251z6wjkkmc99","yvz3NEjMcVQ7sYJm3trFQ","5fvFLLh8nAp2yZZwxk9ku"],"parent":"rEbR1FrKkZzyjo6ahAgm3","data":{}}
