{"id":"cl8p533i8it5xfzxq3doe17","title":"1115-[Angular] 日期","vault":{"fsPath":"vault"},"type":"note","desc":"","links":[{"type":"frontmatterTag","from":{"fname":"0drops.2022.1115-[Angular] 日期","id":"cl8p533i8it5xfzxq3doe17","vaultName":"vault"},"value":"tags.PROG.Angular","alias":"PROG.Angular","xvault":false,"to":{"fname":"tags.PROG.Angular"}}],"anchors":{},"fname":"0drops.2022.1115-[Angular] 日期","updated":1668648663693,"created":1668495848211,"parent":"0YMTMineOCu8QrkzCD9rn","children":[],"data":{},"contentHash":"5bd29c7660ca910249fdd723c627ae2e","custom":{},"tags":["PROG.Angular"]}
