{"id":"hikt5akgz6251z6wjkkmc99","title":"OS","desc":"","updated":1650380320047,"created":1650380320047,"custom":{},"fname":"tags.PROG.OS","type":"note","vault":{"fsPath":"vault"},"contentHash":"2c00180370abeea653eb93bc9ee5aeb6","links":[{"from":{"fname":"0drops.2022.0914-[Ch2Ch3]IO、OS 架構、VM","id":"iwm8cxyx12fpzxdeesvfsiw","vaultName":"vault"},"type":"backlink","value":"tags.PROG.OS"},{"from":{"fname":"drops.2022.0419-[Ch1]作業系統簡介與常見系統類型(二)","id":"tjo1srktkmfjj2wz4e5bn7c","vaultName":"vault"},"type":"backlink","value":"tags.PROG.OS"},{"from":{"fname":"drops.2022.0419-[系列文目錄] OS (一)","id":"e7gwr2vcb0hk4n2yxqn0ha6","vaultName":"vault"},"type":"backlink","value":"tags.PROG.OS"},{"from":{"fname":"drops.2022.0830-WSL2+KVM在win11上測試macos的safari與使用xcode測IOS","id":"o7mp336qqwyjf1d0jefmg53","vaultName":"vault"},"type":"backlink","value":"tags.PROG.OS"}],"anchors":{},"children":[],"parent":"4nZxUaZMBAvz7oWuXizXl","data":{}}
